torchsense/__init__.py
torchsense/datasets/__init__.py
torchsense/datasets/custom.py
torchsense/datasets/folder.py
torchsense/datasets/utils.py
torchsense/datasets/vision.py
torchsense/metrics/__init__.py
torchsense/metrics/kd_losses.py
torchsense/metrics/losses.py
torchsense/metrics/mape.py
torchsense/metrics/triplet.py
torchsense/metrics/weight_loss.py
torchsense/metrics/functional/__init__.py
torchsense/metrics/functional/sisnr.py
torchsense/models/Autoencode.py
torchsense/models/Autoencoder.py
torchsense/models/LSTM.py
torchsense/models/__init__.py
torchsense/models/alexnet.py
torchsense/models/attention.py
torchsense/models/cct.py
torchsense/models/cgan.py
torchsense/models/cnn4.py
torchsense/models/conv_tasnet.py
torchsense/models/conv_tasnet_lite2.py
torchsense/models/deeplab.py
torchsense/models/deeplabv3p.py
torchsense/models/densenet.py
torchsense/models/fsrcnn.py
torchsense/models/gan_g.py
torchsense/models/gan_g2.py
torchsense/models/googlenet.py
torchsense/models/gpt_srgan.py
torchsense/models/inceptionv3.py
torchsense/models/inceptionv4.py
torchsense/models/mobilenet.py
torchsense/models/mobilenetv1.py
torchsense/models/mobilenetv2.py
torchsense/models/mobilenetv3.py
torchsense/models/nasnet.py
torchsense/models/network_rrdbnet.py
torchsense/models/preactresnet.py
torchsense/models/resnet.py
torchsense/models/resnext.py
torchsense/models/rir.py
torchsense/models/rnn.py
torchsense/models/rrdb_cbam.py
torchsense/models/sealex.py
torchsense/models/senet.py
torchsense/models/shufflenet.py
torchsense/models/shufflenetv2.py
torchsense/models/simple_vit_1d.py
torchsense/models/squeezenet.py
torchsense/models/stochasticdepth.py
torchsense/models/unet.py
torchsense/models/unet_lstm.py
torchsense/models/utils.py
torchsense/models/vgg.py
torchsense/models/vit.py
torchsense/models/wideresidual.py
torchsense/models/xception.py
torchsense/trainer/__init__.py
torchsense/trainer/trainer.py
torchsense/trainer/lit_model/__init__.py
torchsense-0.0.15.dist-info/licenses/LICENSE
torchsense-0.0.15.dist-info/METADATA
torchsense-0.0.15.dist-info/WHEEL
torchsense-0.0.15.dist-info/top_level.txt
torchsense-0.0.15.dist-info/RECORD
